[
  {
    "player_name": "Adam Worth",
    "gang_name": "The Worth Gang",
    "score": 100,
    "money_earned": 2000,
    "days_survived": 1,
    "gang_wars_won": 0,
    "fights_won": 2,
    "date_achieved": "2026-03-04 18:47:00"
  },
  {
    "player_name": "Billy the Kid",
    "gang_name": "Billy's Boys",
    "score": 50,
    "money_earned": 1000,
    "days_survived": 1,
    "gang_wars_won": 0,
    "fights_won": 1,
    "date_achieved": "2026-03-04 18:47:00"
  },
  {
    "player_name": "Jesse James",
    "gang_name": "The James Gang",
    "score": 25,
    "money_earned": 500,
    "days_survived": 1,
    "gang_wars_won": 0,
    "fights_won": 0,
    "date_achieved": "2026-03-04 18:47:00"
  },
  {
    "player_name": "Belle Starr",
    "gang_name": "Starr's Outlaws",
    "score": 12,
    "money_earned": 240,
    "days_survived": 1,
    "gang_wars_won": 0,
    "fights_won": 0,
    "date_achieved": "2026-03-04 18:47:00"
  },
  {
    "player_name": "Black Bart",
    "gang_name": "Black Bart's Raiders",
    "score": 6,
    "money_earned": 120,
    "days_survived": 1,
    "gang_wars_won": 0,
    "fights_won": 0,
    "date_achieved": "2026-03-04 18:47:00"
  },
  {
    "player_name": "Soapy Smith",
    "gang_name": "The Soap Gang",
    "score": 3,
    "money_earned": 60,
    "days_survived": 1,
    "gang_wars_won": 0,
    "fights_won": 0,
    "date_achieved": "2026-03-04 18:47:00"
  },
  {
    "player_name": "Sam Bass",
    "gang_name": "Bass's Raiders",
    "score": 1,
    "money_earned": 20,
    "days_survived": 1,
    "gang_wars_won": 0,
    "fights_won": 0,
    "date_achieved": "2026-03-04 18:47:00"
  },
  {
    "player_name": "Cherokee Bill",
    "gang_name": "Cherokee's Crew",
    "score": 1,
    "money_earned": 20,
    "days_survived": 1,
    "gang_wars_won": 0,
    "fights_won": 0,
    "date_achieved": "2026-03-04 18:47:00"
  },
  {
    "player_name": "Johnny Ringo",
    "gang_name": "Ringo's Raiders",
    "score": 1,
    "money_earned": 20,
    "days_survived": 1,
    "gang_wars_won": 0,
    "fights_won": 0,
    "date_achieved": "2026-03-04 18:47:00"
  },
  {
    "player_name": "Curly Bill Brocius",
    "gang_name": "Curly Bill's Bunch",
    "score": 1,
    "money_earned": 20,
    "days_survived": 1,
    "gang_wars_won": 0,
    "fights_won": 0,
    "date_achieved": "2026-03-04 18:47:00"
  }
]